lingvo/model_registry.py
lingvo/pdb_wrapper.py
lingvo/datasets.py
lingvo/model_imports.py
lingvo/__init__.py
lingvo/base_trial.py
lingvo/models_test_helper.py
lingvo/compat.py
lingvo/trainer_utils.py
lingvo/base_runner.py
lingvo/ipython_kernel.py
lingvo/trainer.py
lingvo/runners.py
lingvo/executor.py
lingvo/tools/gke_launch.py
lingvo/tools/compare_params.py
lingvo/tools/__init__.py
lingvo/tools/count_records.py
lingvo/tools/keras2ckpt.py
lingvo/tools/bpe_word_tokenizer.py
lingvo/tools/print_tf_records.py
lingvo/tools/compute_stats.py
lingvo/tools/audio_lib.py
lingvo/tools/create_asr_features.py
lingvo/tools/beam_utils.py
lingvo/tools/wpm_encode_file.py
lingvo/jax/asserts.py
lingvo/jax/train.py
lingvo/jax/test_utils.py
lingvo/jax/model_registry.py
lingvo/jax/summary_utils.py
lingvo/jax/metric_utils.py
lingvo/jax/gshard_utils.py
lingvo/jax/optimizers.py
lingvo/jax/base_model_params.py
lingvo/jax/model_imports.py
lingvo/jax/__init__.py
lingvo/jax/pytypes.py
lingvo/jax/py_utils.py
lingvo/jax/base_layer.py
lingvo/jax/train_states.py
lingvo/jax/partitioning.py
lingvo/jax/trainer_lib.py
lingvo/jax/learners.py
lingvo/jax/schedules.py
lingvo/jax/main.py
lingvo/jax/model_utils.py
lingvo/jax/model.py
lingvo/jax/base_input.py
lingvo/jax/eval.py
lingvo/jax/checkpoints.py
lingvo/jax/layers/flax_wrapper.py
lingvo/jax/layers/__init__.py
lingvo/jax/layers/normalizations.py
lingvo/jax/layers/repeats.py
lingvo/jax/layers/linears.py
lingvo/jax/layers/resnets.py
lingvo/jax/layers/attentions.py
lingvo/jax/layers/test_layers.py
lingvo/jax/layers/ngrammer.py
lingvo/jax/layers/augmentations.py
lingvo/jax/layers/transformers.py
lingvo/jax/layers/recurrent.py
lingvo/jax/layers/embedding_softmax.py
lingvo/jax/layers/activations.py
lingvo/jax/layers/pipeline.py
lingvo/jax/layers/convolutions.py
lingvo/jax/layers/poolings.py
lingvo/jax/layers/stochastics.py
lingvo/jax/mlperf/train.py
lingvo/jax/mlperf/__init__.py
lingvo_jax-0.11.0.dist-info/top_level.txt
lingvo_jax-0.11.0.dist-info/LICENSE
lingvo_jax-0.11.0.dist-info/WHEEL
lingvo_jax-0.11.0.dist-info/METADATA
lingvo_jax-0.11.0.dist-info/RECORD
